{
	"instance" : {
		"compositeTokenVariables" : "Henrique 6/9/2017 18:05",
		"increment_list:" : "Henrique 6/14/2017 15:09",
		"initialization:" : "Henrique 6/12/2017 15:36",
		"increment_list" : "Henrique 6/14/2017 15:09",
		"semicolonTokens:" : "Henrique 6/9/2017 18:05",
		"initialize" : "Henrique 6/14/2017 15:08",
		"exp:" : "Henrique 6/14/2017 15:08",
		"exp" : "Henrique 6/14/2017 15:08",
		"statement" : "Henrique 6/9/2017 18:05",
		"initialization" : "Henrique 6/9/2017 18:05",
		"rightParenToken" : "Henrique 6/9/2017 18:05",
		"leftParenToken" : "Henrique 6/9/2017 18:05",
		"nodeVariables" : "Henrique 6/14/2017 15:09",
		"tokenVariables" : "Henrique 6/9/2017 18:05",
		"leftParenToken:" : "Henrique 6/9/2017 18:05",
		"semicolonTokens" : "Henrique 6/9/2017 18:05",
		"statement:" : "Henrique 6/12/2017 14:55",
		"forToken:" : "Henrique 6/9/2017 18:05",
		"acceptVisitor:" : "Henrique 6/12/2017 15:32",
		"rightParenToken:" : "Henrique 6/9/2017 18:05",
		"forToken" : "Henrique 6/9/2017 18:05"
	},
	"class" : { }
}